cyrc/models.py
cyrc/cyrc.cpython-312-darwin.so
cyrc/cyrc.pyx
cyrc/__init__.py
cyrc-0.1.1.dist-info/RECORD
cyrc-0.1.1.dist-info/LICENSE
cyrc-0.1.1.dist-info/WHEEL
cyrc-0.1.1.dist-info/top_level.txt
cyrc-0.1.1.dist-info/METADATA
