Metadata-Version: 2.1
Name: cyrc
Version: 0.1.1
Summary: Python CRC Calculation Library
Project-URL: Homepage, https://github.com/marzooqy/cyrc
Requires-Python: >=3.7
License-File: LICENSE
